bird2board/__init__.py
bird2board/app.py
bird2board/bird.py
bird2board/bird2board.py
bird2board/board.py
bird2board/test_app.py
bird2board/test_bird.py
bird2board/test_bird2board.py
bird2board/test_pinboard.py
bird2board-0.2.0.dist-info/LICENSE
bird2board-0.2.0.dist-info/METADATA
bird2board-0.2.0.dist-info/WHEEL
bird2board-0.2.0.dist-info/entry_points.txt
bird2board-0.2.0.dist-info/top_level.txt
bird2board-0.2.0.dist-info/RECORD
