Metadata-Version: 2.1
Name: bird2board
Version: 0.2.0
Summary: Convert bird based bookmarks to board based ones.
Home-page: https://github.com/ihuston/bird2board
Author: Ian Huston
Author-email: ian@ianhuston.net
License: MIT
Platform: UNKNOWN
Classifier: Development Status :: 4 - Beta
Classifier: Environment :: Console
Classifier: Intended Audience :: End Users/Desktop
Classifier: License :: OSI Approved :: MIT License
Classifier: Programming Language :: Python :: 3 :: Only
Classifier: Topic :: Utilities
Classifier: Natural Language :: English
License-File: LICENSE
Requires-Dist: requests (~=2.25.1)
Requires-Dist: click (~=8.0.1)
